example-python-plugin/README.md
example-python-plugin/main.py
example-python-plugin/plugin.yaml
example-python-plugin/requirements.txt
xcoding_plugin/__init__.py
xcoding_plugin/cli.py
xcoding_plugin/client.py
xcoding_plugin/exceptions.py
xcoding_plugin-0.1.3.dist-info/METADATA
xcoding_plugin-0.1.3.dist-info/WHEEL
xcoding_plugin-0.1.3.dist-info/entry_points.txt
xcoding_plugin-0.1.3.dist-info/RECORD
