Metadata-Version: 2.4
Name: xcoding-plugin
Version: 0.1.3
Summary: XCoding Plugin Python package for plugin development and management
Project-URL: Homepage, https://github.com/xcoding/plugin
Project-URL: Repository, https://github.com/xcoding/plugin
Project-URL: Documentation, https://xcoding-plugin.readthedocs.io/
Project-URL: Changelog, https://github.com/xcoding/plugin/blob/main/CHANGELOG.md
Requires-Python: >=3.8
Requires-Dist: pyyaml>=6.0
Requires-Dist: requests>=2.25.0
Provides-Extra: dev
Requires-Dist: black>=21.0; extra == 'dev'
Requires-Dist: flake8>=3.8; extra == 'dev'
Requires-Dist: mypy>=0.910; extra == 'dev'
Requires-Dist: pytest>=6.0; extra == 'dev'
